daw_schemas/__init__.py
daw_schemas/daw_format_base.py
daw_schemas/ableton_live/__init__.py
daw_schemas/ableton_live/compare.py
daw_schemas/ableton_live/generate_schema.py
daw_schemas/ableton_live/12/schema.json
daw_schemas-0.1.0.dist-info/METADATA
daw_schemas-0.1.0.dist-info/WHEEL
daw_schemas-0.1.0.dist-info/entry_points.txt
daw_schemas-0.1.0.dist-info/top_level.txt
daw_schemas-0.1.0.dist-info/RECORD
