Metadata-Version: 2.4
Name: daw-schemas
Version: 0.1.0
Summary: JSON schemas for Digital Audio Workstation (DAW) file formats
Author-email: Owen Bush <owen@obush.co.uk>
License-Expression: MIT
Keywords: daw,ableton,music,audio,schema
Classifier: Development Status :: 3 - Alpha
Classifier: Intended Audience :: Developers
Classifier: Programming Language :: Python :: 3
Classifier: Programming Language :: Python :: 3.7
Classifier: Programming Language :: Python :: 3.8
Classifier: Programming Language :: Python :: 3.9
Classifier: Programming Language :: Python :: 3.10
Classifier: Programming Language :: Python :: 3.11
Classifier: Programming Language :: Python :: 3.12
Classifier: Topic :: Multimedia :: Sound/Audio
Classifier: Topic :: Software Development :: Libraries :: Python Modules
Requires-Python: >=3.7
